[
    {
      "continentId": 1,
      "continentName": "South America",
      "territories": [
        {
          "continent": 1,
          "name": "Venezuela",
          "armies": 0,
          "owner": null,
          "neighbors": []
        },
        {
          "continent": 1,
          "name": "Peru",
          "armies": 0,
          "owner": null,
          "neighbors": []
        },
        {
          "continent": 1,
          "name": "Brasile",
          "armies": 0,
          "owner": null,
          "neighbors": []
        },
        {
          "continent": 1,
          "name": "Argentina",
          "armies": 0,
          "owner": null,
          "neighbors": []
        }
      ]
    },
    {
      "continentId": 2,
      "continentName": "Europe",
      "territories": [
        {
          "continent": 2,
          "name": "Islanda",
          "armies": 0,
          "owner": null,
          "neighbors": []
        },
        {
          "continent": 2,
          "name": "Scandinavia",
          "armies": 0,
          "owner": null,
          "neighbors": []
        },
        {
          "continent": 2,
          "name": "Gran Bretagna",
          "armies": 0,
          "owner": null,
          "neighbors": []
        },
        {
          "continent": 2,
          "name": "Europa Occidentale",
          "armies": 0,
          "owner": null,
          "neighbors": []
        },
        {
          "continent": 2,
          "name": "Europa Meridionale",
          "armies": 0,
          "owner": null,
          "neighbors": []
        },
        {
          "continent": 2,
          "name": "Ucraina",
          "armies": 0,
          "owner": null,
          "neighbors": []
        },
        {
          "continent": 2,
          "name": "Europa Settentrionale",
          "armies": 0,
          "owner": null,
          "neighbors": []
        }
      ]
    },
    {
      "continentId": 3,
      "continentName": "Africa",
      "territories": [
        {
          "continent": 3,
          "name": "Africa del Nord",
          "armies": 0,
          "owner": null,
          "neighbors": []
        },
        {
          "continent": 3,
          "name": "Egitto",
          "armies": 0,
          "owner": null,
          "neighbors": []
        },
        {
          "continent": 3,
          "name": "Congo",
          "armies": 0,
          "owner": null,
          "neighbors": []
        },
        {
          "continent": 3,
          "name": "Madagascar",
          "armies": 0,
          "owner": null,
          "neighbors": []
        },
        {
          "continent": 3,
          "name": "Africa Meridionale",
          "armies": 0,
          "owner": null,
          "neighbors": []
        },
        {
          "continent": 3,
          "name": "Africa Orientale",
          "armies": 0,
          "owner": null,
          "neighbors": []
        }
      ]
    },
    {
      "continentId": 4,
      "continentName": "Asia",
      "territories": [
        {
          "continent": 4,
          "name": "Urali",
          "armies": 0,
          "owner": null,
          "neighbors": []
        },
        {
          "continent": 4,
          "name": "Siberia",
          "armies": 0,
          "owner": null,
          "neighbors": []
        },
        {
          "continent": 4,
          "name": "Cina",
          "armies": 0,
          "owner": null,
          "neighbors": []
        },
        {
          "continent": 4,
          "name": "India",
          "armies": 0,
          "owner": null,
          "neighbors": []
        },
        {
          "continent": 4,
          "name": "Medio Oriente",
          "armies": 0,
          "owner": null,
          "neighbors": []
        },
        {
          "continent": 4,
          "name": "Afghanistan",
          "armies": 0,
          "owner": null,
          "neighbors": []
        },
        {
          "continent": 4,
          "name": "Mongolia",
          "armies": 0,
          "owner": null,
          "neighbors": []
        },
        {
          "continent": 4,
          "name": "Giappone",
          "armies": 0,
          "owner": null,
          "neighbors": []
        },
        {
          "continent": 4,
          "name": "Siam",
          "armies": 0,
          "owner": null,
          "neighbors": []
        },
        {
          "continent": 4,
          "name": "Jacuzia",
          "armies": 0,
          "owner": null,
          "neighbors": []
        },
        {
          "continent": 4,
          "name": "Kamchatka",
          "armies": 0,
          "owner": null,
          "neighbors": []
        },
        {
          "continent": 4,
          "name": "Urali",
          "armies": 0,
          "owner": null,
          "neighbors": []
        }
      ]
    },
    {
      "continentId": 5,
      "continentName": "North America",
      "territories": [
        {
          "continent": 5,
          "name": "Alaska",
          "armies": 0,
          "owner": null,
          "neighbors": []
        },
        {
          "continent": 5,
          "name": "Territori del Nord-Ovest",
          "armies": 0,
          "owner": null,
          "neighbors": []
        },
        {
          "continent": 5,
          "name": "Groenlandia",
          "armies": 0,
          "owner": null,
          "neighbors": []
        },
        {
          "continent": 5,
          "name": "Alberta",
          "armies": 0,
          "owner": null,
          "neighbors": []
        },
        {
          "continent": 5,
          "name": "Quebec",
          "armies": 0,
          "owner": null,
          "neighbors": []
        },
        {
          "continent": 5,
          "name": "America Centrale",
          "armies": 0,
          "owner": null,
          "neighbors": []
        },
        {
          "continent": 5,
          "name": "Stati Uniti Orientali",
          "armies": 0,
          "owner": null,
          "neighbors": []
        },
        {
          "continent": 5,
          "name": "Stati Uniti Occidentali",
          "armies": 0,
          "owner": null,
          "neighbors": []
        },
        {
          "continent": 5,
          "name": "Ontario",
          "armies": 0,
          "owner": null,
          "neighbors": []
        }
      ]
    },
    {
      "continentId": 6,
      "continentName": "Oceania",
      "territories": [
        {
          "continent": 6,
          "name": "Indonesia",
          "armies": 0,
          "owner": null,
          "neighbors": []
        },
        {
          "continent": 6,
          "name": "Nuova Guinea",
          "armies": 0,
          "owner": null,
          "neighbors": []
        },
        {
          "continent": 6,
          "name": "Australia Occidentale",
          "armies": 0,
          "owner": null,
          "neighbors": []
        },
        {
          "continent": 6,
          "name": "Australia Orientale",
          "armies": 0,
          "owner": null,
          "neighbors": []
        }
      ]
    }
  ]